{
    "FileVersion": "2.0.0",
    "EnableAddressable": true,
    "LocationToLower": false,
    "IncludeAssetGUID": false,
    "OutputNameStyle": 0,
    "BuildPipeline": "BuiltinBuildPipeline",
    "PackageName": "DefaultPackage",
    "PackageVersion": "25-0611-154219",
    "AssetList": [
        {
            "Address": "3-1-2-1-3-1_增加级别_03",
            "AssetPath": "Assets/[0]Cilent/Textures/3-1-2-1-3-1_增加级别/3-1-2-1-3-1_增加级别_03.jpg",
            "AssetGUID": "",
            "AssetTags": [],
            "BundleID": 0
        },
        {
            "Address": "3-1-2-1-3-1_增加级别_07",
            "AssetPath": "Assets/[0]Cilent/Textures/3-1-2-1-3-1_增加级别/3-1-2-1-3-1_增加级别_07.jpg",
            "AssetGUID": "",
            "AssetTags": [],
            "BundleID": 0
        },
        {
            "Address": "3-1-2-2-1-2_批量增加_03",
            "AssetPath": "Assets/[0]Cilent/Textures/3-1-2-2-1-2_批量增加/3-1-2-2-1-2_批量增加_03.jpg",
            "AssetGUID": "",
            "AssetTags": [],
            "BundleID": 1
        },
        {
            "Address": "3-1-2-2-1-2_批量增加_07",
            "AssetPath": "Assets/[0]Cilent/Textures/3-1-2-2-1-2_批量增加/3-1-2-2-1-2_批量增加_07.jpg",
            "AssetGUID": "",
            "AssetTags": [],
            "BundleID": 1
        },
        {
            "Address": "3-1-2-2-1-2_批量增加_08",
            "AssetPath": "Assets/[0]Cilent/Textures/3-1-2-2-1-2_批量增加/3-1-2-2-1-2_批量增加_08.jpg",
            "AssetGUID": "",
            "AssetTags": [],
            "BundleID": 1
        },
        {
            "Address": "3-1-2-2-1-2_批量增加_12",
            "AssetPath": "Assets/[0]Cilent/Textures/3-1-2-2-1-2_批量增加/3-1-2-2-1-2_批量增加_12.jpg",
            "AssetGUID": "",
            "AssetTags": [],
            "BundleID": 1
        },
        {
            "Address": "3-1_人员信息采集",
            "AssetPath": "Assets/[0]Cilent/Textures/3-1_人员信息采集.png",
            "AssetGUID": "",
            "AssetTags": [],
            "BundleID": 2
        },
        {
            "Address": "3-4-2_客观评估",
            "AssetPath": "Assets/[0]Cilent/Textures/3-4-2_客观评估.png",
            "AssetGUID": "",
            "AssetTags": [],
            "BundleID": 2
        },
        {
            "Address": "3-4_危机预警评估",
            "AssetPath": "Assets/[0]Cilent/Textures/3-4_危机预警评估.png",
            "AssetGUID": "",
            "AssetTags": [],
            "BundleID": 2
        },
        {
            "Address": "3-4_危机预警评估_ (3)",
            "AssetPath": "Assets/[0]Cilent/Textures/3-4_危机预警评估_ (3).png",
            "AssetGUID": "",
            "AssetTags": [],
            "BundleID": 2
        },
        {
            "Address": "3-4_危机预警评估_47",
            "AssetPath": "Assets/[0]Cilent/Textures/3-4_危机预警评估_47.jpg",
            "AssetGUID": "",
            "AssetTags": [],
            "BundleID": 2
        },
        {
            "Address": "3-5-1_个体干预_ (13)",
            "AssetPath": "Assets/[0]Cilent/Textures/3-5-1_个体干预_ (13).jpg",
            "AssetGUID": "",
            "AssetTags": [],
            "BundleID": 2
        },
        {
            "Address": "3-5-1_个体干预_ (14)",
            "AssetPath": "Assets/[0]Cilent/Textures/3-5-1_个体干预_ (14).jpg",
            "AssetGUID": "",
            "AssetTags": [],
            "BundleID": 2
        },
        {
            "Address": "3-5_危机干预实施",
            "AssetPath": "Assets/[0]Cilent/Textures/3-5_危机干预实施.png",
            "AssetGUID": "",
            "AssetTags": [],
            "BundleID": 2
        },
        {
            "Address": "3-6-1-2_客观评估档案",
            "AssetPath": "Assets/[0]Cilent/Textures/3-6-1-2_客观评估档案.png",
            "AssetGUID": "",
            "AssetTags": [],
            "BundleID": 2
        },
        {
            "Address": "3-6-1_评估档案管理",
            "AssetPath": "Assets/[0]Cilent/Textures/3-6-1_评估档案管理.png",
            "AssetGUID": "",
            "AssetTags": [],
            "BundleID": 2
        },
        {
            "Address": "3-6-2_干预档案管理",
            "AssetPath": "Assets/[0]Cilent/Textures/3-6-2_干预档案管理.png",
            "AssetGUID": "",
            "AssetTags": [],
            "BundleID": 2
        },
        {
            "Address": "3-6_危机档案管理",
            "AssetPath": "Assets/[0]Cilent/Textures/3-6_危机档案管理.png",
            "AssetGUID": "",
            "AssetTags": [],
            "BundleID": 2
        },
        {
            "Address": "3-8_系统管理设置",
            "AssetPath": "Assets/[0]Cilent/Textures/3-8_系统管理设置.png",
            "AssetGUID": "",
            "AssetTags": [],
            "BundleID": 2
        },
        {
            "Address": "14",
            "AssetPath": "Assets/[0]Cilent/Textures/14.png",
            "AssetGUID": "",
            "AssetTags": [],
            "BundleID": 2
        },
        {
            "Address": "667d24eb74ec0741549b6f056e868d7",
            "AssetPath": "Assets/[0]Cilent/Textures/667d24eb74ec0741549b6f056e868d7.png",
            "AssetGUID": "",
            "AssetTags": [],
            "BundleID": 2
        },
        {
            "Address": "关于我们",
            "AssetPath": "Assets/[0]Cilent/Textures/关于我们.png",
            "AssetGUID": "",
            "AssetTags": [],
            "BundleID": 2
        },
        {
            "Address": "加载页面",
            "AssetPath": "Assets/[0]Cilent/Textures/加载页面.jpg",
            "AssetGUID": "",
            "AssetTags": [],
            "BundleID": 2
        },
        {
            "Address": "增加级别图片",
            "AssetPath": "Assets/[0]Cilent/Textures/增加级别图片.png",
            "AssetGUID": "",
            "AssetTags": [],
            "BundleID": 2
        },
        {
            "Address": "增加级别图片2",
            "AssetPath": "Assets/[0]Cilent/Textures/增加级别图片2.png",
            "AssetGUID": "",
            "AssetTags": [],
            "BundleID": 2
        },
        {
            "Address": "帮助",
            "AssetPath": "Assets/[0]Cilent/Textures/帮助.png",
            "AssetGUID": "",
            "AssetTags": [],
            "BundleID": 2
        },
        {
            "Address": "3-5_危机干预实施_ (12)",
            "AssetPath": "Assets/[0]Cilent/Textures/危机干预实施/3-5_危机干预实施_ (12).jpg",
            "AssetGUID": "",
            "AssetTags": [],
            "BundleID": 3
        },
        {
            "Address": "3-5_危机干预实施_ (13)",
            "AssetPath": "Assets/[0]Cilent/Textures/危机干预实施/3-5_危机干预实施_ (13).jpg",
            "AssetGUID": "",
            "AssetTags": [],
            "BundleID": 3
        },
        {
            "Address": "Microphone Off",
            "AssetPath": "Assets/[0]Cilent/Textures/危机干预实施/Microphone Off.png",
            "AssetGUID": "",
            "AssetTags": [],
            "BundleID": 3
        },
        {
            "Address": "Microphone",
            "AssetPath": "Assets/[0]Cilent/Textures/危机干预实施/Microphone.png",
            "AssetGUID": "",
            "AssetTags": [],
            "BundleID": 3
        },
        {
            "Address": "选择界面",
            "AssetPath": "Assets/[0]Cilent/Textures/情绪宣泄/选择界面.jpg",
            "AssetGUID": "",
            "AssetTags": [],
            "BundleID": 4
        },
        {
            "Address": "8",
            "AssetPath": "Assets/[0]Cilent/Textures/系统设置管理/8.png",
            "AssetGUID": "",
            "AssetTags": [],
            "BundleID": 5
        },
        {
            "Address": "9",
            "AssetPath": "Assets/[0]Cilent/Textures/系统设置管理/9.png",
            "AssetGUID": "",
            "AssetTags": [],
            "BundleID": 5
        },
        {
            "Address": "10",
            "AssetPath": "Assets/[0]Cilent/Textures/系统设置管理/10.png",
            "AssetGUID": "",
            "AssetTags": [],
            "BundleID": 5
        },
        {
            "Address": "11",
            "AssetPath": "Assets/[0]Cilent/Textures/系统设置管理/11.png",
            "AssetGUID": "",
            "AssetTags": [],
            "BundleID": 5
        },
        {
            "Address": "加载页",
            "AssetPath": "Assets/[0]Cilent/Textures/系统设置管理/加载页.jpg",
            "AssetGUID": "",
            "AssetTags": [],
            "BundleID": 5
        },
        {
            "Address": "系统设置管理",
            "AssetPath": "Assets/[0]Cilent/Textures/系统设置管理/系统设置管理.jpg",
            "AssetGUID": "",
            "AssetTags": [],
            "BundleID": 5
        },
        {
            "Address": "GroupCrisisIncidentOptionConfig",
            "AssetPath": "Assets/[0]Cilent/Config/GroupCrisisIncidentOptionConfig.asset",
            "AssetGUID": "",
            "AssetTags": [],
            "BundleID": 6
        },
        {
            "Address": "HotBadgeConfig",
            "AssetPath": "Assets/[0]Cilent/Config/HotBadgeConfig.asset",
            "AssetGUID": "",
            "AssetTags": [],
            "BundleID": 6
        },
        {
            "Address": "PersonalCrisisEventPropertyConfig",
            "AssetPath": "Assets/[0]Cilent/Config/PersonalCrisisEventPropertyConfig.asset",
            "AssetGUID": "",
            "AssetTags": [],
            "BundleID": 6
        },
        {
            "Address": "ScaleScoringConfig",
            "AssetPath": "Assets/[0]Cilent/Config/ScaleScoringConfig.asset",
            "AssetGUID": "",
            "AssetTags": [],
            "BundleID": 6
        },
        {
            "Address": "AssetBundleCollectorConfig",
            "AssetPath": "Assets/[0]Cilent/Config/YooAssetSetting/AssetBundleCollectorConfig.xml",
            "AssetGUID": "",
            "AssetTags": [],
            "BundleID": 7
        },
        {
            "Address": "LoadProgress",
            "AssetPath": "Assets/[0]Cilent/Prefabs/LoadProgress.prefab",
            "AssetGUID": "",
            "AssetTags": [],
            "BundleID": 8
        },
        {
            "Address": "StartInit",
            "AssetPath": "Assets/[0]Cilent/Prefabs/StartInit.prefab",
            "AssetGUID": "",
            "AssetTags": [],
            "BundleID": 8
        },
        {
            "Address": "LoginPanel_PC",
            "AssetPath": "Assets/[0]Cilent/UI/PC/StartScene/LoginPanel_PC.prefab",
            "AssetGUID": "",
            "AssetTags": [
                "UI"
            ],
            "BundleID": 9
        },
        {
            "Address": "PagePromptBox_PC",
            "AssetPath": "Assets/[0]Cilent/UI/PC/WorkScene/PagePromptBox_PC.prefab",
            "AssetGUID": "",
            "AssetTags": [
                "UI"
            ],
            "BundleID": 10
        },
        {
            "Address": "PersonalPersonnelEntry_PC",
            "AssetPath": "Assets/[0]Cilent/UI/PC/WorkScene/PersonalPersonnelEntry_PC.prefab",
            "AssetGUID": "",
            "AssetTags": [
                "UI"
            ],
            "BundleID": 10
        },
        {
            "Address": "上方栏_PC",
            "AssetPath": "Assets/[0]Cilent/UI/PC/WorkScene/上方栏_PC.prefab",
            "AssetGUID": "",
            "AssetTags": [
                "UI"
            ],
            "BundleID": 10
        },
        {
            "Address": "情绪放松_PC",
            "AssetPath": "Assets/[0]Cilent/UI/PC/WorkScene/情绪放松_PC.prefab",
            "AssetGUID": "",
            "AssetTags": [
                "UI"
            ],
            "BundleID": 10
        },
        {
            "Address": "提示弹窗_PC",
            "AssetPath": "Assets/[0]Cilent/UI/PC/WorkScene/提示弹窗_PC.prefab",
            "AssetGUID": "",
            "AssetTags": [
                "UI"
            ],
            "BundleID": 10
        },
        {
            "Address": "眼动脱敏_PC",
            "AssetPath": "Assets/[0]Cilent/UI/PC/WorkScene/眼动脱敏_PC.prefab",
            "AssetGUID": "",
            "AssetTags": [
                "UI"
            ],
            "BundleID": 10
        },
        {
            "Address": "确认提示弹窗_PC",
            "AssetPath": "Assets/[0]Cilent/UI/PC/WorkScene/确认提示弹窗_PC.prefab",
            "AssetGUID": "",
            "AssetTags": [
                "UI"
            ],
            "BundleID": 10
        },
        {
            "Address": "个人信息管理_PC",
            "AssetPath": "Assets/[0]Cilent/UI/PC/WorkScene/人员信息采集/个人信息管理_PC.prefab",
            "AssetGUID": "",
            "AssetTags": [
                "UI"
            ],
            "BundleID": 11
        },
        {
            "Address": "人员信息采集界面_PC",
            "AssetPath": "Assets/[0]Cilent/UI/PC/WorkScene/人员信息采集/人员信息采集界面_PC.prefab",
            "AssetGUID": "",
            "AssetTags": [
                "UI"
            ],
            "BundleID": 11
        },
        {
            "Address": "关于面板_PC",
            "AssetPath": "Assets/[0]Cilent/UI/PC/WorkScene/人员信息采集/关于面板_PC.prefab",
            "AssetGUID": "",
            "AssetTags": [
                "UI"
            ],
            "BundleID": 11
        },
        {
            "Address": "单个增加人员面板_PC",
            "AssetPath": "Assets/[0]Cilent/UI/PC/WorkScene/人员信息采集/单个增加人员面板_PC.prefab",
            "AssetGUID": "",
            "AssetTags": [
                "UI"
            ],
            "BundleID": 11
        },
        {
            "Address": "团体事件选项_PC",
            "AssetPath": "Assets/[0]Cilent/UI/PC/WorkScene/人员信息采集/团体事件选项_PC.prefab",
            "AssetGUID": "",
            "AssetTags": [
                "UI"
            ],
            "BundleID": 11
        },
        {
            "Address": "团体信息管理_PC",
            "AssetPath": "Assets/[0]Cilent/UI/PC/WorkScene/人员信息采集/团体信息管理_PC.prefab",
            "AssetGUID": "",
            "AssetTags": [
                "UI"
            ],
            "BundleID": 11
        },
        {
            "Address": "团体危机事件人员信息条目_PC",
            "AssetPath": "Assets/[0]Cilent/UI/PC/WorkScene/人员信息采集/团体危机事件人员信息条目_PC.prefab",
            "AssetGUID": "",
            "AssetTags": [
                "UI"
            ],
            "BundleID": 11
        },
        {
            "Address": "团体危机人员显示面板_PC",
            "AssetPath": "Assets/[0]Cilent/UI/PC/WorkScene/人员信息采集/团体危机人员显示面板_PC.prefab",
            "AssetGUID": "",
            "AssetTags": [
                "UI"
            ],
            "BundleID": 11
        },
        {
            "Address": "团体危机显示面板_PC",
            "AssetPath": "Assets/[0]Cilent/UI/PC/WorkScene/人员信息采集/团体危机显示面板_PC.prefab",
            "AssetGUID": "",
            "AssetTags": [
                "UI"
            ],
            "BundleID": 11
        },
        {
            "Address": "团体应激事件添加条目_PC",
            "AssetPath": "Assets/[0]Cilent/UI/PC/WorkScene/人员信息采集/团体应激事件添加条目_PC.prefab",
            "AssetGUID": "",
            "AssetTags": [
                "UI"
            ],
            "BundleID": 11
        },
        {
            "Address": "增加事件面板2_PC",
            "AssetPath": "Assets/[0]Cilent/UI/PC/WorkScene/人员信息采集/增加事件面板2_PC.prefab",
            "AssetGUID": "",
            "AssetTags": [
                "UI"
            ],
            "BundleID": 11
        },
        {
            "Address": "增加事件面板3_PC",
            "AssetPath": "Assets/[0]Cilent/UI/PC/WorkScene/人员信息采集/增加事件面板3_PC.prefab",
            "AssetGUID": "",
            "AssetTags": [
                "UI"
            ],
            "BundleID": 11
        },
        {
            "Address": "增加事件面板_PC",
            "AssetPath": "Assets/[0]Cilent/UI/PC/WorkScene/人员信息采集/增加事件面板_PC.prefab",
            "AssetGUID": "",
            "AssetTags": [
                "UI"
            ],
            "BundleID": 11
        },
        {
            "Address": "增加人员面板_PC",
            "AssetPath": "Assets/[0]Cilent/UI/PC/WorkScene/人员信息采集/增加人员面板_PC.prefab",
            "AssetGUID": "",
            "AssetTags": [
                "UI"
            ],
            "BundleID": 11
        },
        {
            "Address": "多个增加团体危机人员面板_PC",
            "AssetPath": "Assets/[0]Cilent/UI/PC/WorkScene/人员信息采集/多个增加团体危机人员面板_PC.prefab",
            "AssetGUID": "",
            "AssetTags": [
                "UI"
            ],
            "BundleID": 11
        },
        {
            "Address": "帮助面板_PC",
            "AssetPath": "Assets/[0]Cilent/UI/PC/WorkScene/人员信息采集/帮助面板_PC.prefab",
            "AssetGUID": "",
            "AssetTags": [
                "UI"
            ],
            "BundleID": 11
        },
        {
            "Address": "条目编辑栏_PC",
            "AssetPath": "Assets/[0]Cilent/UI/PC/WorkScene/人员信息采集/条目编辑栏_PC.prefab",
            "AssetGUID": "",
            "AssetTags": [
                "UI"
            ],
            "BundleID": 11
        },
        {
            "Address": "级别设置栏_PC",
            "AssetPath": "Assets/[0]Cilent/UI/PC/WorkScene/人员信息采集/级别设置栏_PC.prefab",
            "AssetGUID": "",
            "AssetTags": [
                "UI"
            ],
            "BundleID": 11
        },
        {
            "Address": "3-5-1-1_实施干预目录_PC",
            "AssetPath": "Assets/[0]Cilent/UI/PC/WorkScene/危机干预实施/3-5-1-1_实施干预目录_PC.prefab",
            "AssetGUID": "",
            "AssetTags": [
                "UI"
            ],
            "BundleID": 12
        },
        {
            "Address": "ASK智者1_PC",
            "AssetPath": "Assets/[0]Cilent/UI/PC/WorkScene/危机干预实施/ASK智者1_PC.prefab",
            "AssetGUID": "",
            "AssetTags": [
                "UI"
            ],
            "BundleID": 12
        },
        {
            "Address": "ASK智者_PC",
            "AssetPath": "Assets/[0]Cilent/UI/PC/WorkScene/危机干预实施/ASK智者_PC.prefab",
            "AssetGUID": "",
            "AssetTags": [
                "UI"
            ],
            "BundleID": 12
        },
        {
            "Address": "FSEN_PC",
            "AssetPath": "Assets/[0]Cilent/UI/PC/WorkScene/危机干预实施/FSEN_PC.prefab",
            "AssetGUID": "",
            "AssetTags": [
                "UI"
            ],
            "BundleID": 12
        },
        {
            "Address": "FSEN整幅处理2_PC",
            "AssetPath": "Assets/[0]Cilent/UI/PC/WorkScene/危机干预实施/FSEN整幅处理2_PC.prefab",
            "AssetGUID": "",
            "AssetTags": [
                "UI"
            ],
            "BundleID": 12
        },
        {
            "Address": "FSEN整幅处理3_PC",
            "AssetPath": "Assets/[0]Cilent/UI/PC/WorkScene/危机干预实施/FSEN整幅处理3_PC.prefab",
            "AssetGUID": "",
            "AssetTags": [
                "UI"
            ],
            "BundleID": 12
        },
        {
            "Address": "FSEN整幅处理4_PC",
            "AssetPath": "Assets/[0]Cilent/UI/PC/WorkScene/危机干预实施/FSEN整幅处理4_PC.prefab",
            "AssetGUID": "",
            "AssetTags": [
                "UI"
            ],
            "BundleID": 12
        },
        {
            "Address": "FSEN整幅处理_PC",
            "AssetPath": "Assets/[0]Cilent/UI/PC/WorkScene/危机干预实施/FSEN整幅处理_PC.prefab",
            "AssetGUID": "",
            "AssetTags": [
                "UI"
            ],
            "BundleID": 12
        },
        {
            "Address": "个体档案管理界面_PC",
            "AssetPath": "Assets/[0]Cilent/UI/PC/WorkScene/危机干预实施/个体档案管理界面_PC.prefab",
            "AssetGUID": "",
            "AssetTags": [
                "UI"
            ],
            "BundleID": 12
        },
        {
            "Address": "危机干预实施密码箱1_PC",
            "AssetPath": "Assets/[0]Cilent/UI/PC/WorkScene/危机干预实施/危机干预实施密码箱1_PC.prefab",
            "AssetGUID": "",
            "AssetTags": [
                "UI"
            ],
            "BundleID": 12
        },
        {
            "Address": "危机干预实施密码箱2_PC",
            "AssetPath": "Assets/[0]Cilent/UI/PC/WorkScene/危机干预实施/危机干预实施密码箱2_PC.prefab",
            "AssetGUID": "",
            "AssetTags": [
                "UI"
            ],
            "BundleID": 12
        },
        {
            "Address": "危机干预实施密码箱3_PC",
            "AssetPath": "Assets/[0]Cilent/UI/PC/WorkScene/危机干预实施/危机干预实施密码箱3_PC.prefab",
            "AssetGUID": "",
            "AssetTags": [
                "UI"
            ],
            "BundleID": 12
        },
        {
            "Address": "危机干预实施选择界面_PC",
            "AssetPath": "Assets/[0]Cilent/UI/PC/WorkScene/危机干预实施/危机干预实施选择界面_PC.prefab",
            "AssetGUID": "",
            "AssetTags": [
                "UI"
            ],
            "BundleID": 12
        },
        {
            "Address": "安全岛1_PC",
            "AssetPath": "Assets/[0]Cilent/UI/PC/WorkScene/危机干预实施/安全岛1_PC.prefab",
            "AssetGUID": "",
            "AssetTags": [
                "UI"
            ],
            "BundleID": 12
        },
        {
            "Address": "安全岛_PC",
            "AssetPath": "Assets/[0]Cilent/UI/PC/WorkScene/危机干预实施/安全岛_PC.prefab",
            "AssetGUID": "",
            "AssetTags": [
                "UI"
            ],
            "BundleID": 12
        },
        {
            "Address": "干预实施录制按钮_PC",
            "AssetPath": "Assets/[0]Cilent/UI/PC/WorkScene/危机干预实施/干预实施录制按钮_PC.prefab",
            "AssetGUID": "",
            "AssetTags": [
                "UI"
            ],
            "BundleID": 12
        },
        {
            "Address": "遥控器1_PC",
            "AssetPath": "Assets/[0]Cilent/UI/PC/WorkScene/危机干预实施/遥控器1_PC.prefab",
            "AssetGUID": "",
            "AssetTags": [
                "UI"
            ],
            "BundleID": 12
        },
        {
            "Address": "遥控器2_PC",
            "AssetPath": "Assets/[0]Cilent/UI/PC/WorkScene/危机干预实施/遥控器2_PC.prefab",
            "AssetGUID": "",
            "AssetTags": [
                "UI"
            ],
            "BundleID": 12
        },
        {
            "Address": "遥控器_PC",
            "AssetPath": "Assets/[0]Cilent/UI/PC/WorkScene/危机干预实施/遥控器_PC.prefab",
            "AssetGUID": "",
            "AssetTags": [
                "UI"
            ],
            "BundleID": 12
        },
        {
            "Address": "部分处理1_PC",
            "AssetPath": "Assets/[0]Cilent/UI/PC/WorkScene/危机干预实施/部分处理1_PC.prefab",
            "AssetGUID": "",
            "AssetTags": [
                "UI"
            ],
            "BundleID": 12
        },
        {
            "Address": "部分处理2_PC",
            "AssetPath": "Assets/[0]Cilent/UI/PC/WorkScene/危机干预实施/部分处理2_PC.prefab",
            "AssetGUID": "",
            "AssetTags": [
                "UI"
            ],
            "BundleID": 12
        },
        {
            "Address": "部分处理3_PC",
            "AssetPath": "Assets/[0]Cilent/UI/PC/WorkScene/危机干预实施/部分处理3_PC.prefab",
            "AssetGUID": "",
            "AssetTags": [
                "UI"
            ],
            "BundleID": 12
        },
        {
            "Address": "部分处理4_PC",
            "AssetPath": "Assets/[0]Cilent/UI/PC/WorkScene/危机干预实施/部分处理4_PC.prefab",
            "AssetGUID": "",
            "AssetTags": [
                "UI"
            ],
            "BundleID": 12
        },
        {
            "Address": "部分处理_PC",
            "AssetPath": "Assets/[0]Cilent/UI/PC/WorkScene/危机干预实施/部分处理_PC.prefab",
            "AssetGUID": "",
            "AssetTags": [
                "UI"
            ],
            "BundleID": 12
        },
        {
            "Address": "个体干预查看_PC",
            "AssetPath": "Assets/[0]Cilent/UI/PC/WorkScene/危机档案管理/个体干预查看_PC.prefab",
            "AssetGUID": "",
            "AssetTags": [
                "UI"
            ],
            "BundleID": 13
        },
        {
            "Address": "个体干预档案_PC",
            "AssetPath": "Assets/[0]Cilent/UI/PC/WorkScene/危机档案管理/个体干预档案_PC.prefab",
            "AssetGUID": "",
            "AssetTags": [
                "UI"
            ],
            "BundleID": 13
        },
        {
            "Address": "个体干预档案条目_PC",
            "AssetPath": "Assets/[0]Cilent/UI/PC/WorkScene/危机档案管理/个体干预档案条目_PC.prefab",
            "AssetGUID": "",
            "AssetTags": [
                "UI"
            ],
            "BundleID": 13
        },
        {
            "Address": "主观评估档案_PC",
            "AssetPath": "Assets/[0]Cilent/UI/PC/WorkScene/危机档案管理/主观评估档案_PC.prefab",
            "AssetGUID": "",
            "AssetTags": [
                "UI"
            ],
            "BundleID": 13
        },
        {
            "Address": "主观评估档案条目_PC",
            "AssetPath": "Assets/[0]Cilent/UI/PC/WorkScene/危机档案管理/主观评估档案条目_PC.prefab",
            "AssetGUID": "",
            "AssetTags": [
                "UI"
            ],
            "BundleID": 13
        },
        {
            "Address": "主观评估档案查看_PC",
            "AssetPath": "Assets/[0]Cilent/UI/PC/WorkScene/危机档案管理/主观评估档案查看_PC.prefab",
            "AssetGUID": "",
            "AssetTags": [
                "UI"
            ],
            "BundleID": 13
        },
        {
            "Address": "危机档案管理选择界面_PC",
            "AssetPath": "Assets/[0]Cilent/UI/PC/WorkScene/危机档案管理/危机档案管理选择界面_PC.prefab",
            "AssetGUID": "",
            "AssetTags": [
                "UI"
            ],
            "BundleID": 13
        },
        {
            "Address": "客观评估档案_PC",
            "AssetPath": "Assets/[0]Cilent/UI/PC/WorkScene/危机档案管理/客观评估档案_PC.prefab",
            "AssetGUID": "",
            "AssetTags": [
                "UI"
            ],
            "BundleID": 13
        },
        {
            "Address": "客观评估档案条目_PC",
            "AssetPath": "Assets/[0]Cilent/UI/PC/WorkScene/危机档案管理/客观评估档案条目_PC.prefab",
            "AssetGUID": "",
            "AssetTags": [
                "UI"
            ],
            "BundleID": 13
        },
        {
            "Address": "客观评估档案查看_PC",
            "AssetPath": "Assets/[0]Cilent/UI/PC/WorkScene/危机档案管理/客观评估档案查看_PC.prefab",
            "AssetGUID": "",
            "AssetTags": [
                "UI"
            ],
            "BundleID": 13
        },
        {
            "Address": "干预档案管理界面_PC",
            "AssetPath": "Assets/[0]Cilent/UI/PC/WorkScene/危机档案管理/干预档案管理界面_PC.prefab",
            "AssetGUID": "",
            "AssetTags": [
                "UI"
            ],
            "BundleID": 13
        },
        {
            "Address": "评估档案管理界面_PC",
            "AssetPath": "Assets/[0]Cilent/UI/PC/WorkScene/危机档案管理/评估档案管理界面_PC.prefab",
            "AssetGUID": "",
            "AssetTags": [
                "UI"
            ],
            "BundleID": 13
        },
        {
            "Address": "3-4-1-1-1-1_评估页面3_PC",
            "AssetPath": "Assets/[0]Cilent/UI/PC/WorkScene/危机预警评估/3-4-1-1-1-1_评估页面3_PC.prefab",
            "AssetGUID": "",
            "AssetTags": [
                "UI"
            ],
            "BundleID": 14
        },
        {
            "Address": "3-4-1-1-1评估页面2_PC",
            "AssetPath": "Assets/[0]Cilent/UI/PC/WorkScene/危机预警评估/3-4-1-1-1评估页面2_PC.prefab",
            "AssetGUID": "",
            "AssetTags": [
                "UI"
            ],
            "BundleID": 14
        },
        {
            "Address": "3-4-1-1评估页面_PC",
            "AssetPath": "Assets/[0]Cilent/UI/PC/WorkScene/危机预警评估/3-4-1-1评估页面_PC.prefab",
            "AssetGUID": "",
            "AssetTags": [
                "UI"
            ],
            "BundleID": 14
        },
        {
            "Address": "3-4-2-1-1_开始客观评估_PC",
            "AssetPath": "Assets/[0]Cilent/UI/PC/WorkScene/危机预警评估/3-4-2-1-1_开始客观评估_PC.prefab",
            "AssetGUID": "",
            "AssetTags": [
                "UI"
            ],
            "BundleID": 14
        },
        {
            "Address": "3-4-2-1_客观评估页面_PC",
            "AssetPath": "Assets/[0]Cilent/UI/PC/WorkScene/危机预警评估/3-4-2-1_客观评估页面_PC.prefab",
            "AssetGUID": "",
            "AssetTags": [
                "UI"
            ],
            "BundleID": 14
        },
        {
            "Address": "危机评估预警界面_PC",
            "AssetPath": "Assets/[0]Cilent/UI/PC/WorkScene/危机预警评估/危机评估预警界面_PC.prefab",
            "AssetGUID": "",
            "AssetTags": [
                "UI"
            ],
            "BundleID": 14
        },
        {
            "Address": "危机预警主观评估_PC",
            "AssetPath": "Assets/[0]Cilent/UI/PC/WorkScene/危机预警评估/危机预警主观评估_PC.prefab",
            "AssetGUID": "",
            "AssetTags": [
                "UI"
            ],
            "BundleID": 14
        },
        {
            "Address": "危机预警客观评估_PC",
            "AssetPath": "Assets/[0]Cilent/UI/PC/WorkScene/危机预警评估/危机预警客观评估_PC.prefab",
            "AssetGUID": "",
            "AssetTags": [
                "UI"
            ],
            "BundleID": 14
        },
        {
            "Address": "客观评估选项_PC",
            "AssetPath": "Assets/[0]Cilent/UI/PC/WorkScene/危机预警评估/客观评估选项_PC.prefab",
            "AssetGUID": "",
            "AssetTags": [
                "UI"
            ],
            "BundleID": 14
        },
        {
            "Address": "情绪选项_PC",
            "AssetPath": "Assets/[0]Cilent/UI/PC/WorkScene/危机预警评估/情绪选项_PC.prefab",
            "AssetGUID": "",
            "AssetTags": [
                "UI"
            ],
            "BundleID": 14
        },
        {
            "Address": "等级滑动条_PC",
            "AssetPath": "Assets/[0]Cilent/UI/PC/WorkScene/危机预警评估/等级滑动条_PC.prefab",
            "AssetGUID": "",
            "AssetTags": [
                "UI"
            ],
            "BundleID": 14
        },
        {
            "Address": "行为选项_PC",
            "AssetPath": "Assets/[0]Cilent/UI/PC/WorkScene/危机预警评估/行为选项_PC.prefab",
            "AssetGUID": "",
            "AssetTags": [
                "UI"
            ],
            "BundleID": 14
        },
        {
            "Address": "认知选项_PC",
            "AssetPath": "Assets/[0]Cilent/UI/PC/WorkScene/危机预警评估/认知选项_PC.prefab",
            "AssetGUID": "",
            "AssetTags": [
                "UI"
            ],
            "BundleID": 14
        },
        {
            "Address": "评估量表条目_PC",
            "AssetPath": "Assets/[0]Cilent/UI/PC/WorkScene/危机预警评估/评估量表条目_PC.prefab",
            "AssetGUID": "",
            "AssetTags": [
                "UI"
            ],
            "BundleID": 14
        },
        {
            "Address": "干预资源库危机干预案例_PC",
            "AssetPath": "Assets/[0]Cilent/UI/PC/WorkScene/干预资源库/干预资源库危机干预案例_PC.prefab",
            "AssetGUID": "",
            "AssetTags": [
                "UI"
            ],
            "BundleID": 15
        },
        {
            "Address": "干预资源库干预方法指导_PC",
            "AssetPath": "Assets/[0]Cilent/UI/PC/WorkScene/干预资源库/干预资源库干预方法指导_PC.prefab",
            "AssetGUID": "",
            "AssetTags": [
                "UI"
            ],
            "BundleID": 15
        },
        {
            "Address": "干预资源库手册查看_PC",
            "AssetPath": "Assets/[0]Cilent/UI/PC/WorkScene/干预资源库/干预资源库手册查看_PC.prefab",
            "AssetGUID": "",
            "AssetTags": [
                "UI"
            ],
            "BundleID": 15
        },
        {
            "Address": "干预资源库选项栏_PC",
            "AssetPath": "Assets/[0]Cilent/UI/PC/WorkScene/干预资源库/干预资源库选项栏_PC.prefab",
            "AssetGUID": "",
            "AssetTags": [
                "UI"
            ],
            "BundleID": 15
        },
        {
            "Address": "干预资源库面板_PC",
            "AssetPath": "Assets/[0]Cilent/UI/PC/WorkScene/干预资源库/干预资源库面板_PC.prefab",
            "AssetGUID": "",
            "AssetTags": [
                "UI"
            ],
            "BundleID": 15
        },
        {
            "Address": "增加管理员面板_PC",
            "AssetPath": "Assets/[0]Cilent/UI/PC/WorkScene/系统设置管理/增加管理员面板_PC.prefab",
            "AssetGUID": "",
            "AssetTags": [
                "UI"
            ],
            "BundleID": 16
        },
        {
            "Address": "界面管理底图（2)_PC",
            "AssetPath": "Assets/[0]Cilent/UI/PC/WorkScene/系统设置管理/界面管理底图（2)_PC.prefab",
            "AssetGUID": "",
            "AssetTags": [
                "UI"
            ],
            "BundleID": 16
        },
        {
            "Address": "管理人员显示条目_PC",
            "AssetPath": "Assets/[0]Cilent/UI/PC/WorkScene/系统设置管理/管理人员显示条目_PC.prefab",
            "AssetGUID": "",
            "AssetTags": [
                "UI"
            ],
            "BundleID": 16
        },
        {
            "Address": "管理员管理_PC",
            "AssetPath": "Assets/[0]Cilent/UI/PC/WorkScene/系统设置管理/管理员管理_PC.prefab",
            "AssetGUID": "",
            "AssetTags": [
                "UI"
            ],
            "BundleID": 16
        },
        {
            "Address": "系统设置界面管理界面_PC",
            "AssetPath": "Assets/[0]Cilent/UI/PC/WorkScene/系统设置管理/系统设置界面管理界面_PC.prefab",
            "AssetGUID": "",
            "AssetTags": [
                "UI"
            ],
            "BundleID": 16
        },
        {
            "Address": "通知_PC",
            "AssetPath": "Assets/[0]Cilent/UI/PC/通知_PC.prefab",
            "AssetGUID": "",
            "AssetTags": [
                "UI"
            ],
            "BundleID": 17
        },
        {
            "Address": "GameStartScene",
            "AssetPath": "Assets/[0]Cilent/Scenes/GameStartScene.unity",
            "AssetGUID": "",
            "AssetTags": [],
            "BundleID": 18
        },
        {
            "Address": "HotFixScene",
            "AssetPath": "Assets/[0]Cilent/Scenes/HotFixScene.unity",
            "AssetGUID": "",
            "AssetTags": [],
            "BundleID": 18
        },
        {
            "Address": "MainChooseScene",
            "AssetPath": "Assets/[0]Cilent/Scenes/MainChooseScene.unity",
            "AssetGUID": "",
            "AssetTags": [],
            "BundleID": 18
        },
        {
            "Address": "StartLoginScene",
            "AssetPath": "Assets/[0]Cilent/Scenes/StartLoginScene.unity",
            "AssetGUID": "",
            "AssetTags": [],
            "BundleID": 18
        },
        {
            "Address": "test",
            "AssetPath": "Assets/[0]Cilent/Scenes/test.unity",
            "AssetGUID": "",
            "AssetTags": [],
            "BundleID": 18
        },
        {
            "Address": "WorkScene",
            "AssetPath": "Assets/[0]Cilent/Scenes/WorkScene.unity",
            "AssetGUID": "",
            "AssetTags": [],
            "BundleID": 18
        },
        {
            "Address": "LoginPanel_Mobile",
            "AssetPath": "Assets/[0]Cilent/UI/Modlie/StartScene/LoginPanel_Mobile.prefab",
            "AssetGUID": "",
            "AssetTags": [
                "UI"
            ],
            "BundleID": 19
        },
        {
            "Address": "PersonalPersonnelEntry_Mobile",
            "AssetPath": "Assets/[0]Cilent/UI/Modlie/WorkScene/人员信息采集/PersonalPersonnelEntry_Mobile.prefab",
            "AssetGUID": "",
            "AssetTags": [
                "UI"
            ],
            "BundleID": 20
        },
        {
            "Address": "个人信息管理_Mobile",
            "AssetPath": "Assets/[0]Cilent/UI/Modlie/WorkScene/人员信息采集/个人信息管理_Mobile.prefab",
            "AssetGUID": "",
            "AssetTags": [
                "UI"
            ],
            "BundleID": 20
        },
        {
            "Address": "个人信息管理面板_Mobile",
            "AssetPath": "Assets/[0]Cilent/UI/Modlie/WorkScene/人员信息采集/个人信息管理面板_Mobile.prefab",
            "AssetGUID": "",
            "AssetTags": [
                "UI"
            ],
            "BundleID": 20
        },
        {
            "Address": "人员信息采集界面_Mobile",
            "AssetPath": "Assets/[0]Cilent/UI/Modlie/WorkScene/人员信息采集/人员信息采集界面_Mobile.prefab",
            "AssetGUID": "",
            "AssetTags": [
                "UI"
            ],
            "BundleID": 20
        },
        {
            "Address": "关于面板_Mobile",
            "AssetPath": "Assets/[0]Cilent/UI/Modlie/WorkScene/人员信息采集/关于面板_Mobile.prefab",
            "AssetGUID": "",
            "AssetTags": [
                "UI"
            ],
            "BundleID": 20
        },
        {
            "Address": "单个增加人员面板_Mobile",
            "AssetPath": "Assets/[0]Cilent/UI/Modlie/WorkScene/人员信息采集/单个增加人员面板_Mobile.prefab",
            "AssetGUID": "",
            "AssetTags": [
                "UI"
            ],
            "BundleID": 20
        },
        {
            "Address": "团体信息管理_Mobile",
            "AssetPath": "Assets/[0]Cilent/UI/Modlie/WorkScene/人员信息采集/团体信息管理_Mobile.prefab",
            "AssetGUID": "",
            "AssetTags": [
                "UI"
            ],
            "BundleID": 20
        },
        {
            "Address": "团体危机事件人员信息条目_Mobile",
            "AssetPath": "Assets/[0]Cilent/UI/Modlie/WorkScene/人员信息采集/团体危机事件人员信息条目_Mobile.prefab",
            "AssetGUID": "",
            "AssetTags": [
                "UI"
            ],
            "BundleID": 20
        },
        {
            "Address": "团体危机人员显示面板_Mobile",
            "AssetPath": "Assets/[0]Cilent/UI/Modlie/WorkScene/人员信息采集/团体危机人员显示面板_Mobile.prefab",
            "AssetGUID": "",
            "AssetTags": [
                "UI"
            ],
            "BundleID": 20
        },
        {
            "Address": "团体危机显示面板_Mobile",
            "AssetPath": "Assets/[0]Cilent/UI/Modlie/WorkScene/人员信息采集/团体危机显示面板_Mobile.prefab",
            "AssetGUID": "",
            "AssetTags": [
                "UI"
            ],
            "BundleID": 20
        },
        {
            "Address": "增加事件面板3_Mobile",
            "AssetPath": "Assets/[0]Cilent/UI/Modlie/WorkScene/人员信息采集/增加事件面板3_Mobile.prefab",
            "AssetGUID": "",
            "AssetTags": [
                "UI"
            ],
            "BundleID": 20
        },
        {
            "Address": "增加事件面板_Mobile",
            "AssetPath": "Assets/[0]Cilent/UI/Modlie/WorkScene/人员信息采集/增加事件面板_Mobile.prefab",
            "AssetGUID": "",
            "AssetTags": [
                "UI"
            ],
            "BundleID": 20
        },
        {
            "Address": "多个增加团体危机人员面板_Mobile",
            "AssetPath": "Assets/[0]Cilent/UI/Modlie/WorkScene/人员信息采集/多个增加团体危机人员面板_Mobile.prefab",
            "AssetGUID": "",
            "AssetTags": [
                "UI"
            ],
            "BundleID": 20
        },
        {
            "Address": "帮助面板_Mobile",
            "AssetPath": "Assets/[0]Cilent/UI/Modlie/WorkScene/人员信息采集/帮助面板_Mobile.prefab",
            "AssetGUID": "",
            "AssetTags": [
                "UI"
            ],
            "BundleID": 20
        },
        {
            "Address": "3-5-1-1_实施干预目录_Mobile",
            "AssetPath": "Assets/[0]Cilent/UI/Modlie/WorkScene/危机干预实施/3-5-1-1_实施干预目录_Mobile.prefab",
            "AssetGUID": "",
            "AssetTags": [
                "UI"
            ],
            "BundleID": 21
        },
        {
            "Address": "ASK智者1_Mobile",
            "AssetPath": "Assets/[0]Cilent/UI/Modlie/WorkScene/危机干预实施/ASK智者1_Mobile.prefab",
            "AssetGUID": "",
            "AssetTags": [
                "UI"
            ],
            "BundleID": 21
        },
        {
            "Address": "ASK智者_Mobile",
            "AssetPath": "Assets/[0]Cilent/UI/Modlie/WorkScene/危机干预实施/ASK智者_Mobile.prefab",
            "AssetGUID": "",
            "AssetTags": [
                "UI"
            ],
            "BundleID": 21
        },
        {
            "Address": "FSEN_Mobile",
            "AssetPath": "Assets/[0]Cilent/UI/Modlie/WorkScene/危机干预实施/FSEN_Mobile.prefab",
            "AssetGUID": "",
            "AssetTags": [
                "UI"
            ],
            "BundleID": 21
        },
        {
            "Address": "FSEN整幅处理2_Mobile",
            "AssetPath": "Assets/[0]Cilent/UI/Modlie/WorkScene/危机干预实施/FSEN整幅处理2_Mobile.prefab",
            "AssetGUID": "",
            "AssetTags": [
                "UI"
            ],
            "BundleID": 21
        },
        {
            "Address": "FSEN整幅处理3_Mobile",
            "AssetPath": "Assets/[0]Cilent/UI/Modlie/WorkScene/危机干预实施/FSEN整幅处理3_Mobile.prefab",
            "AssetGUID": "",
            "AssetTags": [
                "UI"
            ],
            "BundleID": 21
        },
        {
            "Address": "FSEN整幅处理4_Mobile",
            "AssetPath": "Assets/[0]Cilent/UI/Modlie/WorkScene/危机干预实施/FSEN整幅处理4_Mobile.prefab",
            "AssetGUID": "",
            "AssetTags": [
                "UI"
            ],
            "BundleID": 21
        },
        {
            "Address": "FSEN整幅处理_Mobile",
            "AssetPath": "Assets/[0]Cilent/UI/Modlie/WorkScene/危机干预实施/FSEN整幅处理_Mobile.prefab",
            "AssetGUID": "",
            "AssetTags": [
                "UI"
            ],
            "BundleID": 21
        },
        {
            "Address": "个体档案管理界面_Mobile",
            "AssetPath": "Assets/[0]Cilent/UI/Modlie/WorkScene/危机干预实施/个体档案管理界面_Mobile.prefab",
            "AssetGUID": "",
            "AssetTags": [
                "UI"
            ],
            "BundleID": 21
        },
        {
            "Address": "危机干预实施密码箱1_Mobile",
            "AssetPath": "Assets/[0]Cilent/UI/Modlie/WorkScene/危机干预实施/危机干预实施密码箱1_Mobile.prefab",
            "AssetGUID": "",
            "AssetTags": [
                "UI"
            ],
            "BundleID": 21
        },
        {
            "Address": "危机干预实施密码箱2_Mobile",
            "AssetPath": "Assets/[0]Cilent/UI/Modlie/WorkScene/危机干预实施/危机干预实施密码箱2_Mobile.prefab",
            "AssetGUID": "",
            "AssetTags": [
                "UI"
            ],
            "BundleID": 21
        },
        {
            "Address": "危机干预实施密码箱3_Mobile",
            "AssetPath": "Assets/[0]Cilent/UI/Modlie/WorkScene/危机干预实施/危机干预实施密码箱3_Mobile.prefab",
            "AssetGUID": "",
            "AssetTags": [
                "UI"
            ],
            "BundleID": 21
        },
        {
            "Address": "危机干预实施选择界面_Mobile",
            "AssetPath": "Assets/[0]Cilent/UI/Modlie/WorkScene/危机干预实施/危机干预实施选择界面_Mobile.prefab",
            "AssetGUID": "",
            "AssetTags": [
                "UI"
            ],
            "BundleID": 21
        },
        {
            "Address": "安全岛1_Mobile",
            "AssetPath": "Assets/[0]Cilent/UI/Modlie/WorkScene/危机干预实施/安全岛1_Mobile.prefab",
            "AssetGUID": "",
            "AssetTags": [
                "UI"
            ],
            "BundleID": 21
        },
        {
            "Address": "安全岛_Mobile",
            "AssetPath": "Assets/[0]Cilent/UI/Modlie/WorkScene/危机干预实施/安全岛_Mobile.prefab",
            "AssetGUID": "",
            "AssetTags": [
                "UI"
            ],
            "BundleID": 21
        },
        {
            "Address": "遥控器1_Mobile",
            "AssetPath": "Assets/[0]Cilent/UI/Modlie/WorkScene/危机干预实施/遥控器1_Mobile.prefab",
            "AssetGUID": "",
            "AssetTags": [
                "UI"
            ],
            "BundleID": 21
        },
        {
            "Address": "遥控器2_Mobile",
            "AssetPath": "Assets/[0]Cilent/UI/Modlie/WorkScene/危机干预实施/遥控器2_Mobile.prefab",
            "AssetGUID": "",
            "AssetTags": [
                "UI"
            ],
            "BundleID": 21
        },
        {
            "Address": "遥控器_Mobile",
            "AssetPath": "Assets/[0]Cilent/UI/Modlie/WorkScene/危机干预实施/遥控器_Mobile.prefab",
            "AssetGUID": "",
            "AssetTags": [
                "UI"
            ],
            "BundleID": 21
        },
        {
            "Address": "部分处理1_Mobile",
            "AssetPath": "Assets/[0]Cilent/UI/Modlie/WorkScene/危机干预实施/部分处理1_Mobile.prefab",
            "AssetGUID": "",
            "AssetTags": [
                "UI"
            ],
            "BundleID": 21
        },
        {
            "Address": "部分处理2_Mobile",
            "AssetPath": "Assets/[0]Cilent/UI/Modlie/WorkScene/危机干预实施/部分处理2_Mobile.prefab",
            "AssetGUID": "",
            "AssetTags": [
                "UI"
            ],
            "BundleID": 21
        },
        {
            "Address": "部分处理3_Mobile",
            "AssetPath": "Assets/[0]Cilent/UI/Modlie/WorkScene/危机干预实施/部分处理3_Mobile.prefab",
            "AssetGUID": "",
            "AssetTags": [
                "UI"
            ],
            "BundleID": 21
        },
        {
            "Address": "部分处理4_Mobile",
            "AssetPath": "Assets/[0]Cilent/UI/Modlie/WorkScene/危机干预实施/部分处理4_Mobile.prefab",
            "AssetGUID": "",
            "AssetTags": [
                "UI"
            ],
            "BundleID": 21
        },
        {
            "Address": "部分处理_Mobile",
            "AssetPath": "Assets/[0]Cilent/UI/Modlie/WorkScene/危机干预实施/部分处理_Mobile.prefab",
            "AssetGUID": "",
            "AssetTags": [
                "UI"
            ],
            "BundleID": 21
        },
        {
            "Address": "3-4-1-1-1评估页面2_Mobile",
            "AssetPath": "Assets/[0]Cilent/UI/Modlie/WorkScene/危机预警评估/3-4-1-1-1评估页面2_Mobile.prefab",
            "AssetGUID": "",
            "AssetTags": [
                "UI"
            ],
            "BundleID": 22
        },
        {
            "Address": "3-4-1-1评估页面_Mobile",
            "AssetPath": "Assets/[0]Cilent/UI/Modlie/WorkScene/危机预警评估/3-4-1-1评估页面_Mobile.prefab",
            "AssetGUID": "",
            "AssetTags": [
                "UI"
            ],
            "BundleID": 22
        },
        {
            "Address": "危机评估预警界面_Mobile",
            "AssetPath": "Assets/[0]Cilent/UI/Modlie/WorkScene/危机预警评估/危机评估预警界面_Mobile.prefab",
            "AssetGUID": "",
            "AssetTags": [
                "UI"
            ],
            "BundleID": 22
        },
        {
            "Address": "危机预警主观评估_Mobile",
            "AssetPath": "Assets/[0]Cilent/UI/Modlie/WorkScene/危机预警评估/危机预警主观评估_Mobile.prefab",
            "AssetGUID": "",
            "AssetTags": [
                "UI"
            ],
            "BundleID": 22
        },
        {
            "Address": "增加部门面板_Mobile",
            "AssetPath": "Assets/[0]Cilent/UI/Modlie/WorkScene/系统设置管理/增加部门面板_Mobile.prefab",
            "AssetGUID": "",
            "AssetTags": [
                "UI"
            ],
            "BundleID": 23
        },
        {
            "Address": "界面管理底图（2）_Mobile",
            "AssetPath": "Assets/[0]Cilent/UI/Modlie/WorkScene/系统设置管理/界面管理底图（2）_Mobile.prefab",
            "AssetGUID": "",
            "AssetTags": [
                "UI"
            ],
            "BundleID": 23
        },
        {
            "Address": "系统管理选择界面_Mobile",
            "AssetPath": "Assets/[0]Cilent/UI/Modlie/WorkScene/系统设置管理/系统管理选择界面_Mobile.prefab",
            "AssetGUID": "",
            "AssetTags": [
                "UI"
            ],
            "BundleID": 23
        },
        {
            "Address": "系统设置界面管理界面_Mobile",
            "AssetPath": "Assets/[0]Cilent/UI/Modlie/WorkScene/系统设置管理/系统设置界面管理界面_Mobile.prefab",
            "AssetGUID": "",
            "AssetTags": [
                "UI"
            ],
            "BundleID": 23
        },
        {
            "Address": "部门信息条目_Mobile",
            "AssetPath": "Assets/[0]Cilent/UI/Modlie/WorkScene/系统设置管理/部门信息条目_Mobile.prefab",
            "AssetGUID": "",
            "AssetTags": [
                "UI"
            ],
            "BundleID": 23
        },
        {
            "Address": "部门信息管理_Mobile",
            "AssetPath": "Assets/[0]Cilent/UI/Modlie/WorkScene/系统设置管理/部门信息管理_Mobile.prefab",
            "AssetGUID": "",
            "AssetTags": [
                "UI"
            ],
            "BundleID": 23
        },
        {
            "Address": "通知_Mobile",
            "AssetPath": "Assets/[0]Cilent/UI/Modlie/通知_Mobile.prefab",
            "AssetGUID": "",
            "AssetTags": [
                "UI"
            ],
            "BundleID": 24
        }
    ],
    "BundleList": [
        {
            "BundleName": "defaultpackage_assets_[0]cilent_textures_3-1-2-1-3-1_增加级别.bundle",
            "UnityCRC": 78131270,
            "FileHash": "9f508198d4ddcea142bcbe27fb85bf19",
            "FileCRC": "8e1918c7",
            "FileSize": 20609,
            "Encrypted": false,
            "Tags": [
                "UI"
            ],
            "DependIDs": []
        },
        {
            "BundleName": "defaultpackage_assets_[0]cilent_textures_3-1-2-2-1-2_批量增加.bundle",
            "UnityCRC": 538836372,
            "FileHash": "cac258e197f6e3b9447c9b6c05d5e633",
            "FileCRC": "5afd2fd0",
            "FileSize": 55986,
            "Encrypted": false,
            "Tags": [
                "UI"
            ],
            "DependIDs": []
        },
        {
            "BundleName": "defaultpackage_assets_[0]cilent_textures.bundle",
            "UnityCRC": 279618529,
            "FileHash": "356d94c2a12d0ab2964655dea2acf13a",
            "FileCRC": "3afd055c",
            "FileSize": 3113130,
            "Encrypted": false,
            "Tags": [
                "UI"
            ],
            "DependIDs": []
        },
        {
            "BundleName": "defaultpackage_assets_[0]cilent_textures_危机干预实施.bundle",
            "UnityCRC": 1190579188,
            "FileHash": "fa25834bcd99a7ad67f08f564d04e1b8",
            "FileCRC": "4e86611f",
            "FileSize": 138684,
            "Encrypted": false,
            "Tags": [
                "UI"
            ],
            "DependIDs": []
        },
        {
            "BundleName": "defaultpackage_assets_[0]cilent_textures_情绪宣泄.bundle",
            "UnityCRC": 1239397261,
            "FileHash": "e5116d951498551a77571c1dfd74d893",
            "FileCRC": "90e166e0",
            "FileSize": 385920,
            "Encrypted": false,
            "Tags": [],
            "DependIDs": []
        },
        {
            "BundleName": "defaultpackage_assets_[0]cilent_textures_系统设置管理.bundle",
            "UnityCRC": 2440782611,
            "FileHash": "1808c7479162cdbf0471d88036671cc5",
            "FileCRC": "f77175ac",
            "FileSize": 473331,
            "Encrypted": false,
            "Tags": [
                "UI"
            ],
            "DependIDs": []
        },
        {
            "BundleName": "defaultpackage_assets_[0]cilent_config.bundle",
            "UnityCRC": 1100597204,
            "FileHash": "80a4c2b35f4393a41e99c8faf394a7cc",
            "FileCRC": "f6ba4701",
            "FileSize": 161430,
            "Encrypted": false,
            "Tags": [],
            "DependIDs": []
        },
        {
            "BundleName": "defaultpackage_assets_[0]cilent_config_yooassetsetting.bundle",
            "UnityCRC": 3290793661,
            "FileHash": "0a961536976ad93cae5d6b6a08076a0a",
            "FileCRC": "18e3b6e8",
            "FileSize": 2645,
            "Encrypted": false,
            "Tags": [],
            "DependIDs": []
        },
        {
            "BundleName": "defaultpackage_assets_[0]cilent_prefabs.bundle",
            "UnityCRC": 2725753214,
            "FileHash": "3833d79e63c7d9c9f0cb4692bcf503f2",
            "FileCRC": "6640d610",
            "FileSize": 5602,
            "Encrypted": false,
            "Tags": [],
            "DependIDs": [
                26
            ]
        },
        {
            "BundleName": "defaultpackage_assets_[0]cilent_ui_pc_startscene.bundle",
            "UnityCRC": 2875486373,
            "FileHash": "222601b46a03510addfd0b94453974e6",
            "FileCRC": "ce6d0bc1",
            "FileSize": 19808,
            "Encrypted": false,
            "Tags": [
                "UI"
            ],
            "DependIDs": [
                28,
                30,
                26
            ]
        },
        {
            "BundleName": "defaultpackage_assets_[0]cilent_ui_pc_workscene.bundle",
            "UnityCRC": 643864859,
            "FileHash": "6d0d92d5da508afa8d90def7d5547711",
            "FileCRC": "529ae405",
            "FileSize": 29415,
            "Encrypted": false,
            "Tags": [
                "UI"
            ],
            "DependIDs": [
                2,
                28,
                30,
                69,
                68,
                26,
                32,
                31,
                33
            ]
        },
        {
            "BundleName": "defaultpackage_assets_[0]cilent_ui_pc_workscene_人员信息采集.bundle",
            "UnityCRC": 1796868111,
            "FileHash": "0f4512f730e454ee2f699ac94f8c04de",
            "FileCRC": "7a665325",
            "FileSize": 232045,
            "Encrypted": false,
            "Tags": [
                "UI"
            ],
            "DependIDs": [
                2,
                0,
                1,
                35,
                30,
                39,
                41,
                38,
                40,
                52,
                50,
                51,
                49,
                48,
                47,
                75,
                45,
                26,
                32,
                53,
                31,
                33,
                37,
                36,
                42,
                43,
                46,
                54,
                34
            ]
        },
        {
            "BundleName": "defaultpackage_assets_[0]cilent_ui_pc_workscene_危机干预实施.bundle",
            "UnityCRC": 3958537604,
            "FileHash": "06dd562ba9a101771c74f3f8b9eea1a6",
            "FileCRC": "79bb8be4",
            "FileSize": 240019,
            "Encrypted": false,
            "Tags": [
                "UI"
            ],
            "DependIDs": [
                2,
                35,
                30,
                55,
                60,
                41,
                38,
                40,
                50,
                59,
                56,
                57,
                51,
                49,
                58,
                26,
                33,
                34
            ]
        },
        {
            "BundleName": "defaultpackage_assets_[0]cilent_ui_pc_workscene_危机档案管理.bundle",
            "UnityCRC": 3123932839,
            "FileHash": "a1bb0b818732e8e4e11581aa59fe463d",
            "FileCRC": "69e332e8",
            "FileSize": 80363,
            "Encrypted": false,
            "Tags": [
                "UI"
            ],
            "DependIDs": [
                2,
                30,
                61,
                63,
                62,
                26,
                32,
                31,
                33
            ]
        },
        {
            "BundleName": "defaultpackage_assets_[0]cilent_ui_pc_workscene_危机预警评估.bundle",
            "UnityCRC": 2642573027,
            "FileHash": "3c49e0433ef8b83ff5d6153402fc3ad9",
            "FileCRC": "b12c3ce3",
            "FileSize": 114498,
            "Encrypted": false,
            "Tags": [
                "UI"
            ],
            "DependIDs": [
                2,
                30,
                64,
                65,
                26,
                32,
                31,
                33
            ]
        },
        {
            "BundleName": "defaultpackage_assets_[0]cilent_ui_pc_workscene_干预资源库.bundle",
            "UnityCRC": 3200609911,
            "FileHash": "ed63ef8424525a25a390f084ff1e5801",
            "FileCRC": "5b583dec",
            "FileSize": 20227,
            "Encrypted": false,
            "Tags": [
                "UI"
            ],
            "DependIDs": [
                66,
                67,
                26
            ]
        },
        {
            "BundleName": "defaultpackage_assets_[0]cilent_ui_pc_workscene_系统设置管理.bundle",
            "UnityCRC": 1970231976,
            "FileHash": "5b8808d07a3bd89ee974d7851d903dde",
            "FileCRC": "d666b98d",
            "FileSize": 54031,
            "Encrypted": false,
            "Tags": [
                "UI"
            ],
            "DependIDs": [
                2,
                35,
                30,
                41,
                38,
                40,
                50,
                59,
                56,
                57,
                49,
                58,
                26,
                32,
                31,
                33,
                34
            ]
        },
        {
            "BundleName": "defaultpackage_assets_[0]cilent_ui_pc.bundle",
            "UnityCRC": 2906996634,
            "FileHash": "844226281b63dc2e049a2b405047ef33",
            "FileCRC": "56f750e0",
            "FileSize": 9579,
            "Encrypted": false,
            "Tags": [
                "UI"
            ],
            "DependIDs": [
                35,
                70,
                38,
                40,
                50,
                49,
                71,
                58,
                34
            ]
        },
        {
            "BundleName": "defaultpackage_assets_[0]cilent_scenes.bundle",
            "UnityCRC": 2602588526,
            "FileHash": "738a5d819209ce1db542a43e6f025f24",
            "FileCRC": "aa9c1997",
            "FileSize": 83794,
            "Encrypted": false,
            "Tags": [],
            "DependIDs": [
                8,
                2,
                1,
                20,
                35,
                27,
                28,
                72,
                30,
                74,
                76,
                39,
                41,
                73,
                38,
                40,
                52,
                50,
                51,
                49,
                47,
                75,
                45,
                26,
                32,
                53,
                31,
                33,
                37,
                36,
                42,
                43,
                46,
                54,
                34
            ]
        },
        {
            "BundleName": "defaultpackage_assets_[0]cilent_ui_modlie_startscene.bundle",
            "UnityCRC": 3517364890,
            "FileHash": "8306fd6a70f5cce26276ce166184a2c9",
            "FileCRC": "3fc0326e",
            "FileSize": 22252,
            "Encrypted": false,
            "Tags": [
                "UI"
            ],
            "DependIDs": [
                35,
                28,
                30,
                26,
                34
            ]
        },
        {
            "BundleName": "defaultpackage_assets_[0]cilent_ui_modlie_workscene_人员信息采集.bundle",
            "UnityCRC": 2332237524,
            "FileHash": "37f44e16b624c58809e44d43f9c2e0df",
            "FileCRC": "eb48f4b2",
            "FileSize": 193537,
            "Encrypted": false,
            "Tags": [
                "UI"
            ],
            "DependIDs": [
                2,
                1,
                35,
                30,
                39,
                41,
                38,
                40,
                52,
                50,
                51,
                49,
                47,
                75,
                45,
                26,
                32,
                53,
                31,
                33,
                37,
                36,
                42,
                43,
                46,
                54,
                34
            ]
        },
        {
            "BundleName": "defaultpackage_assets_[0]cilent_ui_modlie_workscene_危机干预实施.bundle",
            "UnityCRC": 2192449254,
            "FileHash": "aae2f902d83ee1b8acefa590d0717a4b",
            "FileCRC": "714ce94b",
            "FileSize": 255974,
            "Encrypted": false,
            "Tags": [
                "UI"
            ],
            "DependIDs": [
                2,
                3,
                35,
                30,
                55,
                60,
                41,
                38,
                40,
                50,
                59,
                56,
                57,
                51,
                49,
                58,
                26,
                33,
                34
            ]
        },
        {
            "BundleName": "defaultpackage_assets_[0]cilent_ui_modlie_workscene_危机预警评估.bundle",
            "UnityCRC": 2881560632,
            "FileHash": "614426037b9919d5133ceed2bf2a3381",
            "FileCRC": "9bcff40b",
            "FileSize": 55370,
            "Encrypted": false,
            "Tags": [
                "UI"
            ],
            "DependIDs": [
                2,
                35,
                30,
                26,
                33,
                34
            ]
        },
        {
            "BundleName": "defaultpackage_assets_[0]cilent_ui_modlie_workscene_系统设置管理.bundle",
            "UnityCRC": 734319378,
            "FileHash": "e0dbd6ae7100b0418ae14ad92ca268a6",
            "FileCRC": "f8fc2485",
            "FileSize": 64114,
            "Encrypted": false,
            "Tags": [
                "UI"
            ],
            "DependIDs": [
                2,
                5,
                35,
                30,
                41,
                38,
                40,
                50,
                59,
                56,
                57,
                51,
                49,
                48,
                58,
                26,
                32,
                31,
                33,
                34
            ]
        },
        {
            "BundleName": "defaultpackage_assets_[0]cilent_ui_modlie.bundle",
            "UnityCRC": 3963903973,
            "FileHash": "5df9954ca6e3518345817761c2c3a5f9",
            "FileCRC": "1b4df769",
            "FileSize": 9607,
            "Encrypted": false,
            "Tags": [
                "UI"
            ],
            "DependIDs": [
                35,
                70,
                38,
                40,
                50,
                49,
                71,
                58,
                34
            ]
        },
        {
            "BundleName": "defaultpackage_share_assets_proceduraluiimage_editor.bundle",
            "UnityCRC": 2837306730,
            "FileHash": "0be8cc1607cfe160e16dcb41f324561b",
            "FileCRC": "3ece912d",
            "FileSize": 1197,
            "Encrypted": false,
            "Tags": [],
            "DependIDs": []
        },
        {
            "BundleName": "defaultpackage_share_assets_proceduraluiimage_resources.bundle",
            "UnityCRC": 773907762,
            "FileHash": "7d5b4b9bddeec6e6a77f98e0f1fa8fd7",
            "FileCRC": "88507fbb",
            "FileSize": 4172,
            "Encrypted": false,
            "Tags": [
                "UI"
            ],
            "DependIDs": []
        },
        {
            "BundleName": "defaultpackage_share_assets_[0]cilent_ui.bundle",
            "UnityCRC": 3114626303,
            "FileHash": "61151f01f7d8bd3cc1085cfcbdd2c81c",
            "FileCRC": "4f70e0b6",
            "FileSize": 14286,
            "Encrypted": false,
            "Tags": [],
            "DependIDs": [
                35,
                28,
                41,
                38,
                40,
                50,
                26,
                34
            ]
        },
        {
            "BundleName": "defaultpackage_share_assets_[1]local_textures.bundle",
            "UnityCRC": 1748302585,
            "FileHash": "0f48c89e85d5678f5ee9ba2929f3d741",
            "FileCRC": "683b2da4",
            "FileSize": 17654,
            "Encrypted": false,
            "Tags": [
                "UI"
            ],
            "DependIDs": []
        },
        {
            "BundleName": "defaultpackage_share_packages_com_unity_textmeshpro_editor_resources_gizmos.bundle",
            "UnityCRC": 556029928,
            "FileHash": "127762a7da2fdf561a6f8e85ec7ade1a",
            "FileCRC": "26ccb356",
            "FileSize": 1294,
            "Encrypted": false,
            "Tags": [],
            "DependIDs": []
        },
        {
            "BundleName": "defaultpackage_share_assets_[1]local_textures_mainscene.bundle",
            "UnityCRC": 19864067,
            "FileHash": "2ee299b6735dd526afafd01425f5bc7f",
            "FileCRC": "b9189d31",
            "FileSize": 212369,
            "Encrypted": false,
            "Tags": [
                "UI"
            ],
            "DependIDs": []
        },
        {
            "BundleName": "defaultpackage_share_assets_testpackages_guipack-clean&minimalist_sources_icons_icons_circles_png.bundle",
            "UnityCRC": 3871936365,
            "FileHash": "c19652cbeeedecfc88a05cac77a5935a",
            "FileCRC": "cacc3a35",
            "FileSize": 23884,
            "Encrypted": false,
            "Tags": [
                "UI"
            ],
            "DependIDs": []
        },
        {
            "BundleName": "defaultpackage_share_assets_testpackages_guipack-clean&minimalist_sources_game_controller_game_controller_steam_white_png.bundle",
            "UnityCRC": 1436196172,
            "FileHash": "00db66bf1f9129e910a9c68224a6471d",
            "FileCRC": "dd003f4c",
            "FileSize": 75156,
            "Encrypted": false,
            "Tags": [
                "UI"
            ],
            "DependIDs": []
        },
        {
            "BundleName": "defaultpackage_share_assets_testpackages_guipack-clean&minimalist_sources_icons_icons_png.bundle",
            "UnityCRC": 575264717,
            "FileHash": "21d24d72d67d15f622209b36ab34837d",
            "FileCRC": "1cd42d78",
            "FileSize": 116573,
            "Encrypted": false,
            "Tags": [
                "UI"
            ],
            "DependIDs": []
        },
        {
            "BundleName": "defaultpackage_unityshaders.bundle",
            "UnityCRC": 37096265,
            "FileHash": "8a9636427f564b038529c4d0844a9ca1",
            "FileCRC": "1c72f567",
            "FileSize": 33660,
            "Encrypted": false,
            "Tags": [
                "UI"
            ],
            "DependIDs": []
        },
        {
            "BundleName": "defaultpackage_share_assets_[0]cilent_fonts.bundle",
            "UnityCRC": 924098700,
            "FileHash": "7cc257cec5467bd27cbb38a0708ffd52",
            "FileCRC": "2eaa1bdd",
            "FileSize": 11156937,
            "Encrypted": false,
            "Tags": [
                "UI"
            ],
            "DependIDs": [
                34
            ]
        },
        {
            "BundleName": "defaultpackage_share_assets_textmesh_pro_resources_fonts_&_materials.bundle",
            "UnityCRC": 2094557396,
            "FileHash": "7a980e2532f01db05dd5d9c340f9c66e",
            "FileCRC": "eedae090",
            "FileSize": 373492,
            "Encrypted": false,
            "Tags": [
                "UI"
            ],
            "DependIDs": [
                37,
                34
            ]
        },
        {
            "BundleName": "defaultpackage_share_assets_textmesh_pro_fonts.bundle",
            "UnityCRC": 4292739588,
            "FileHash": "635962a93c8fc4b9d444cf355288437c",
            "FileCRC": "3984ce31",
            "FileSize": 227286,
            "Encrypted": false,
            "Tags": [
                "UI"
            ],
            "DependIDs": []
        },
        {
            "BundleName": "defaultpackage_share_assets_modern_ui_pack_editor_icons.bundle",
            "UnityCRC": 1065395310,
            "FileHash": "ecb0c2670f9b8898998f92f783a60f9d",
            "FileCRC": "a0f95a96",
            "FileSize": 138832,
            "Encrypted": false,
            "Tags": [
                "UI"
            ],
            "DependIDs": []
        },
        {
            "BundleName": "defaultpackage_share_assets_modern_ui_pack_animations_dropdown.bundle",
            "UnityCRC": 766287498,
            "FileHash": "ea3522020d3c14bd52fff1fbc5984f75",
            "FileCRC": "96ed096a",
            "FileSize": 10886,
            "Encrypted": false,
            "Tags": [
                "UI"
            ],
            "DependIDs": []
        },
        {
            "BundleName": "defaultpackage_share_assets_modern_ui_pack_fonts.bundle",
            "UnityCRC": 1505661478,
            "FileHash": "c5ab8044cd769baa5d67c48d6d50b493",
            "FileCRC": "49e7882c",
            "FileSize": 1267336,
            "Encrypted": false,
            "Tags": [
                "UI"
            ],
            "DependIDs": [
                34
            ]
        },
        {
            "BundleName": "defaultpackage_share_assets_modern_ui_pack_animations_input_field.bundle",
            "UnityCRC": 3586851602,
            "FileHash": "09a53ebad22e5d4af818eda8ebf2c0d1",
            "FileCRC": "0e775210",
            "FileSize": 10983,
            "Encrypted": false,
            "Tags": [
                "UI"
            ],
            "DependIDs": []
        },
        {
            "BundleName": "defaultpackage_share_assets_ui_datepicker_fonts.bundle",
            "UnityCRC": 4014253436,
            "FileHash": "8316aff6c0ef03d902aaf6e447d91620",
            "FileCRC": "7e77643d",
            "FileSize": 117151,
            "Encrypted": false,
            "Tags": [
                "UI"
            ],
            "DependIDs": [
                34
            ]
        },
        {
            "BundleName": "defaultpackage_share_assets_ui_datepicker_resources_sprites.bundle",
            "UnityCRC": 2252045081,
            "FileHash": "0c230c876a2560ff1fbaa4e481b8084a",
            "FileCRC": "d98bafd3",
            "FileSize": 5740,
            "Encrypted": false,
            "Tags": [
                "UI"
            ],
            "DependIDs": []
        },
        {
            "BundleName": "defaultpackage_share_assets_modern_ui_pack_editor_resources.bundle",
            "UnityCRC": 3244213699,
            "FileHash": "cf5f8e67a6de0c4fc2c2f98a9837a257",
            "FileCRC": "7f875b0d",
            "FileSize": 17489,
            "Encrypted": false,
            "Tags": [],
            "DependIDs": [
                38,
                40,
                34
            ]
        },
        {
            "BundleName": "defaultpackage_share_assets_modern_ui_pack_textures_icon_others.bundle",
            "UnityCRC": 1087206993,
            "FileHash": "35127b9cfc96a81a701bc8200ca80b33",
            "FileCRC": "dabd9f19",
            "FileSize": 4606,
            "Encrypted": false,
            "Tags": [
                "UI"
            ],
            "DependIDs": []
        },
        {
            "BundleName": "defaultpackage_share_assets_ui_datepicker_sprites.bundle",
            "UnityCRC": 4135433795,
            "FileHash": "ff717f9fe3a01e0874cc238501f6cfb8",
            "FileCRC": "ec63a765",
            "FileSize": 6373,
            "Encrypted": false,
            "Tags": [
                "UI"
            ],
            "DependIDs": []
        },
        {
            "BundleName": "defaultpackage_share_assets_modern_ui_pack_textures_icon_media.bundle",
            "UnityCRC": 4264525411,
            "FileHash": "c1515514124d7bdbda1a1ab54fd46c5f",
            "FileCRC": "a4b40753",
            "FileSize": 5897,
            "Encrypted": false,
            "Tags": [
                "UI"
            ],
            "DependIDs": []
        },
        {
            "BundleName": "defaultpackage_share_assets_modern_ui_pack_textures_border_rounded_64px.bundle",
            "UnityCRC": 2007418048,
            "FileHash": "3633c6954f6f425b663fefb6d5bdc868",
            "FileCRC": "4cd82d93",
            "FileSize": 4337,
            "Encrypted": false,
            "Tags": [
                "UI"
            ],
            "DependIDs": []
        },
        {
            "BundleName": "defaultpackage_share_assets_modern_ui_pack_textures_border_rounded_256px.bundle",
            "UnityCRC": 2197910650,
            "FileHash": "32f61a4a641fa49c3d64c558d3b04696",
            "FileCRC": "097ce5b3",
            "FileSize": 5011,
            "Encrypted": false,
            "Tags": [
                "UI"
            ],
            "DependIDs": []
        },
        {
            "BundleName": "defaultpackage_share_assets_modern_ui_pack_resources.bundle",
            "UnityCRC": 2910987019,
            "FileHash": "165e3cb8764b64f74f11ad755d4f5ca0",
            "FileCRC": "1ef03bc6",
            "FileSize": 4645,
            "Encrypted": false,
            "Tags": [
                "UI"
            ],
            "DependIDs": [
                35,
                40,
                34
            ]
        },
        {
            "BundleName": "defaultpackage_share_assets_modern_ui_pack_textures_border_rounded_128px.bundle",
            "UnityCRC": 3972681875,
            "FileHash": "9738d507f687666cb55ee09f85039c69",
            "FileCRC": "def37176",
            "FileSize": 4983,
            "Encrypted": false,
            "Tags": [
                "UI"
            ],
            "DependIDs": []
        },
        {
            "BundleName": "defaultpackage_share_assets_modern_ui_pack_prefabs_dropdown.bundle",
            "UnityCRC": 583069384,
            "FileHash": "495e8e11a0a3eb0c77f4d444a68eba87",
            "FileCRC": "471fe6c7",
            "FileSize": 9259,
            "Encrypted": false,
            "Tags": [
                "UI"
            ],
            "DependIDs": [
                35,
                40,
                50,
                49,
                47,
                75,
                34
            ]
        },
        {
            "BundleName": "defaultpackage_share_assets_testpackages_guipack-clean&minimalist_sources_game_controller_game_controller_xboxone_white_png.bundle",
            "UnityCRC": 3859404605,
            "FileHash": "2bfab574c1cefc4cae9999c9637aefea",
            "FileCRC": "3ec02981",
            "FileSize": 12735,
            "Encrypted": false,
            "Tags": [
                "UI"
            ],
            "DependIDs": []
        },
        {
            "BundleName": "defaultpackage_share_assets_ui_tablelayout_resources_sprites.bundle",
            "UnityCRC": 4264464481,
            "FileHash": "23551be22bc48c0a55190cbfecb119c0",
            "FileCRC": "0d10b43f",
            "FileSize": 7280,
            "Encrypted": false,
            "Tags": [
                "UI"
            ],
            "DependIDs": []
        },
        {
            "BundleName": "defaultpackage_share_assets_[1]local_textures_ui_微信背景文字ui_3-5-1-1_实施干预目录.bundle",
            "UnityCRC": 61118026,
            "FileHash": "80c8cc86b2d97711c267f0ac54802092",
            "FileCRC": "c6bd94ee",
            "FileSize": 251964,
            "Encrypted": false,
            "Tags": [
                "UI"
            ],
            "DependIDs": []
        },
        {
            "BundleName": "defaultpackage_share_assets_modern_ui_pack_textures_border_radial_64px.bundle",
            "UnityCRC": 4236735809,
            "FileHash": "70b2126852a30b8ada710d2c0b9741ef",
            "FileCRC": "09d42ce9",
            "FileSize": 4910,
            "Encrypted": false,
            "Tags": [
                "UI"
            ],
            "DependIDs": []
        },
        {
            "BundleName": "defaultpackage_share_assets_modern_ui_pack_textures_border_rounded_1024px.bundle",
            "UnityCRC": 2577520378,
            "FileHash": "5597ad9881682e1b42b6e1b22b812551",
            "FileCRC": "22823ff0",
            "FileSize": 10856,
            "Encrypted": false,
            "Tags": [
                "UI"
            ],
            "DependIDs": []
        },
        {
            "BundleName": "defaultpackage_share_assets_modern_ui_pack_textures_shadow.bundle",
            "UnityCRC": 3752075310,
            "FileHash": "abdaba3939b81b6507c3caed9d0ecb17",
            "FileCRC": "c811592e",
            "FileSize": 16585,
            "Encrypted": false,
            "Tags": [
                "UI"
            ],
            "DependIDs": []
        },
        {
            "BundleName": "defaultpackage_share_assets_modern_ui_pack_textures_border_radial_256px.bundle",
            "UnityCRC": 1283054101,
            "FileHash": "7a60f53e455752e3fb44dc3a60f0dc09",
            "FileCRC": "f5ca718a",
            "FileSize": 7164,
            "Encrypted": false,
            "Tags": [
                "UI"
            ],
            "DependIDs": []
        },
        {
            "BundleName": "defaultpackage_share_assets_[1]local_ui_ui参考背景_裁图.bundle",
            "UnityCRC": 876609654,
            "FileHash": "52f0637b18b3533b66f3aaeaf72d44ba",
            "FileCRC": "80fd885a",
            "FileSize": 219571,
            "Encrypted": false,
            "Tags": [
                "UI"
            ],
            "DependIDs": []
        },
        {
            "BundleName": "defaultpackage_share_assets_[1]local_textures_ui_微信背景文字ui_3-6-1-1-2-1_查看.bundle",
            "UnityCRC": 4281615060,
            "FileHash": "37360c4b2c94b3822eda8fd5ae9793e6",
            "FileCRC": "f0b6c84b",
            "FileSize": 14443,
            "Encrypted": false,
            "Tags": [
                "UI"
            ],
            "DependIDs": []
        },
        {
            "BundleName": "defaultpackage_share_assets_[1]local_textures_ui_微信背景文字ui_3-6-2-3-2_查看.bundle",
            "UnityCRC": 4239980784,
            "FileHash": "b7102f76e506c8066929fd6a5bc5f7ee",
            "FileCRC": "619d1eed",
            "FileSize": 6756,
            "Encrypted": false,
            "Tags": [
                "UI"
            ],
            "DependIDs": []
        },
        {
            "BundleName": "defaultpackage_share_assets_[1]local_textures_ui_微信背景文字ui_3-6-1-2-2-1_查看.bundle",
            "UnityCRC": 1685153956,
            "FileHash": "2d47b13ddb644d608484b74d1025fcf0",
            "FileCRC": "14f1ed25",
            "FileSize": 15937,
            "Encrypted": false,
            "Tags": [
                "UI"
            ],
            "DependIDs": []
        },
        {
            "BundleName": "defaultpackage_share_assets_[1]local_textures_ui_微信背景文字ui_3-4-2-1-1_开始客观评估.bundle",
            "UnityCRC": 2320497435,
            "FileHash": "f70707ba8dd1bc2d5c4a32e9fd4240f8",
            "FileCRC": "f8a06714",
            "FileSize": 17890,
            "Encrypted": false,
            "Tags": [
                "UI"
            ],
            "DependIDs": []
        },
        {
            "BundleName": "defaultpackage_share_assets_[1]local_textures_ui_微信背景文字ui_3-4-2-1_客观评估页面.bundle",
            "UnityCRC": 779572754,
            "FileHash": "943840cbbd776b618b21f8a5790b84d2",
            "FileCRC": "14bf3661",
            "FileSize": 17418,
            "Encrypted": false,
            "Tags": [
                "UI"
            ],
            "DependIDs": []
        },
        {
            "BundleName": "defaultpackage_share_assets_[1]local_textures_ui_微信背景文字ui_3-6-2-4-2_查看（右）.bundle",
            "UnityCRC": 3843062227,
            "FileHash": "ca48459bea31d544f3e5c3bb7a6eba28",
            "FileCRC": "17435d0a",
            "FileSize": 93786,
            "Encrypted": false,
            "Tags": [
                "UI"
            ],
            "DependIDs": []
        },
        {
            "BundleName": "defaultpackage_share_assets_[1]local_textures_ui_微信背景文字ui_3-6-2-4-2_查看（左）.bundle",
            "UnityCRC": 2700708795,
            "FileHash": "21067ea0a34313c6b637b6e792b123ee",
            "FileCRC": "874d50ec",
            "FileSize": 5942,
            "Encrypted": false,
            "Tags": [
                "UI"
            ],
            "DependIDs": []
        },
        {
            "BundleName": "defaultpackage_share_assets_[1]local_vedio.bundle",
            "UnityCRC": 2616565586,
            "FileHash": "7276768323423c994e235964ae14891d",
            "FileCRC": "8d128119",
            "FileSize": 1780,
            "Encrypted": false,
            "Tags": [
                "UI"
            ],
            "DependIDs": []
        },
        {
            "BundleName": "defaultpackage_share_assets_[1]local_textures_ui_微信背景文字ui_3-5-1-6_情绪放松.bundle",
            "UnityCRC": 722876333,
            "FileHash": "83201355d87e0d8d0da52738c596cae9",
            "FileCRC": "3c368d37",
            "FileSize": 1447351,
            "Encrypted": false,
            "Tags": [
                "UI"
            ],
            "DependIDs": []
        },
        {
            "BundleName": "defaultpackage_share_assets_modern_ui_pack_animations_notifications.bundle",
            "UnityCRC": 413698374,
            "FileHash": "ac50c8ce6b7bf55f14acdabf21ed1abb",
            "FileCRC": "904c1189",
            "FileSize": 10743,
            "Encrypted": false,
            "Tags": [
                "UI"
            ],
            "DependIDs": []
        },
        {
            "BundleName": "defaultpackage_share_assets_modern_ui_pack_textures_icon_common.bundle",
            "UnityCRC": 3619265847,
            "FileHash": "13ed216306f9b8860b90082b0c9ef83b",
            "FileCRC": "692e9be7",
            "FileSize": 6062,
            "Encrypted": false,
            "Tags": [
                "UI"
            ],
            "DependIDs": []
        },
        {
            "BundleName": "defaultpackage_share_assets_[1]local_textures_hotinit.bundle",
            "UnityCRC": 3974368199,
            "FileHash": "595c68bb541c11b5436b14355794fde3",
            "FileCRC": "a32e0990",
            "FileSize": 53533,
            "Encrypted": false,
            "Tags": [],
            "DependIDs": []
        },
        {
            "BundleName": "defaultpackage_share_assets_modern_ui_pack_animations_progress_bar.bundle",
            "UnityCRC": 3974773183,
            "FileHash": "a0e4db805ea6543c12d28c24bba07422",
            "FileCRC": "725b7329",
            "FileSize": 9554,
            "Encrypted": false,
            "Tags": [],
            "DependIDs": []
        },
        {
            "BundleName": "defaultpackage_share_assets_[1]local_textures_ui.bundle",
            "UnityCRC": 3834208173,
            "FileHash": "199dedc946eb7d7ffe91562c54b2c348",
            "FileCRC": "c714fa2a",
            "FileSize": 1866294,
            "Encrypted": false,
            "Tags": [],
            "DependIDs": []
        },
        {
            "BundleName": "defaultpackage_share_assets_modern_ui_pack_textures_icon_navigation.bundle",
            "UnityCRC": 2434938308,
            "FileHash": "e4521442aceea9fcb96febc11bb960db",
            "FileCRC": "6b89ae32",
            "FileSize": 4830,
            "Encrypted": false,
            "Tags": [
                "UI"
            ],
            "DependIDs": []
        },
        {
            "BundleName": "defaultpackage_share_assets_[1]local_ui_ui参考背景.bundle",
            "UnityCRC": 625056115,
            "FileHash": "2100b967450750e98abdbf756cef4b3a",
            "FileCRC": "499ee117",
            "FileSize": 264270,
            "Encrypted": false,
            "Tags": [],
            "DependIDs": []
        }
    ]
}